<?xml version="1.0" encoding="UTF-8" ?>
<language>

<!-- Naming Scheme: 5554 -> Hexadecimal Ascii for UT; 
10 for Player choices; 20 for Logbook Entries + 
1 for Player Logo Extension
2 for Bridge Commands Extension
3 for Command and Control Extension

301 and 302 for Expression Object Naming (not using the previous Scheme)
301 + 302 : Expression and Replacement (for static Replacements)
303: Dynamic Expressions delivered by Script (DO NOT TRANSLATE; USE EXPRESSION ABOVE TO INSERT TRANSLATED STRING INSTEAD)

Ranges for 301:
0-999: User-Definied Strings (free for the User to use)
1000-1999: Translation-Definied Strings (for translation of Game Language to common language, like english)
2000-2999: Pre-Defined static Replacements

How Expressions are marked:
/*** is a Static Replacement (applied first)
$***** is a Script-defined dnyamic Replacement (applied second;based on a )
%***** is a Engine-based dynamic Replacement (applied third, based on Entries in Page 303 id 1-999)

-->

<!-- This is the Base File - do not Translate or change, it is maintained by the Mod itself -->
<page id="5554301" title="Object Name Expressions" descr="UT Command and Control" voice="no">
  <!-- Even Number is the Expression, directly following Odd Number is the Replacement -->
  <!-- User Defined Part (feel free to add your own her ebut dont forget to add the Result String in the next Page, same ID ;) -->
  <t id="0">/expression</t>
  <t id="1">result</t>
  <t id="2">/colortest</t>
  <t id="3">\033AA\033BB\033CC\033GG\033MM\033RR\033UU\033WW\033XX\033YY\033ZZ{5554302,2013}0</t>
  <t id="4">/skillexpressiontest</t>
  <t id="5">%SCA %SCB %SCC %SCE %SCL %SCM %SCN %SCO %SCS %SDA %SDB %SDC %SDE %SDL %SDM %SDN %SDO %SDS %SEA %SEB %SEC %SEE %SEL %SEM %SEN %SEO %SES</t>
  <t id="6">/nameexpressiontest</t>
  <t id="7">%type %zone %sector %cluster</t>
  <!--  Translation Defined Part -->
  <!-- Color Codes -->
  <!--<t id="1000">/gr1</t> gray 1 -->
  <t id="1001">/gr1</t><!-- gray 1 -->
  <t id="1002">/bla</t><!-- blue -->
  <t id="1003">/blu</t><!-- blue -->
  <!--<t id="1004">/cya</t> cyan -->
  <t id="1005">/cya</t><!-- cyan -->
  <!--<t id="1006">/grn</t> green -->
  <t id="1007">/grn</t><!-- green -->
  <!--<t id="1008">/mag</t> magenta -->
  <t id="1009">/mag</t><!-- magenta -->
  <t id="1010">/rot</t>
  <t id="1011">/red</t>
  <t id="1012">/hbl</t><!--light blue -->
  <t id="1013">/lbl</t><!--light blue -->
  <t id="1014">/wei</t><!-- white -->
  <t id="1015">/whi</t><!-- white -->
  <!--<t id="1016">/nor</t> Regular Color -->
  <t id="1017">/nor</t><!-- Regular Color -->
  <t id="1018">/gel</t><!-- yellow -->
  <t id="1019">/yel</t><!-- yellow -->
  <!--<t id="1020">/gr2</t> gray 2 -->
  <t id="1021">/gr2</t><!-- gray 2 -->
  <t id="1022">/swa</t><!-- black -->
  <t id="1023">/blk</t><!-- black -->
  <!-- Core Replacements -->
  <!-- Color Codes -->
  <t id="2000">/gr1</t><!-- gray 1 -->
  <t id="2001">\033A</t><!-- gray 1 -->
  <t id="2002">/blu</t><!-- blue -->
  <t id="2003">\033B</t><!-- blue -->
  <t id="2004">/cya</t><!-- cyan -->
  <t id="2005">\033C</t><!-- cyan -->
  <t id="2006">/grn</t><!-- green -->
  <t id="2007">\033G</t><!-- green -->
  <t id="2008">/mag</t><!-- magenta -->
  <t id="2009">\033M</t><!-- magenta -->
  <t id="2010">/red</t>
  <t id="2011">\033R</t>
  <t id="2012">/lbl</t><!--light blue -->
  <t id="2013">\033U</t><!--light blue -->
  <t id="2014">/whi</t><!-- white -->
  <t id="2015">\033W</t><!-- white -->
  <t id="2016">/nor</t><!-- Regular Color -->
  <t id="2017">\033X</t><!-- Regular Color -->
  <t id="2018">/yel</t><!-- yellow -->
  <t id="2019">\033Y</t><!-- yellow -->
  <t id="2020">/gr2</t><!-- gray 2 -->
  <t id="2021">\033Z</t><!-- gray 2 -->
  <t id="2022">/blk</t><!-- black -->
  <t id="2023">{5554301,2025}0</t><!-- black -->
  <!--<t id="2024">/033 0</t> black (technical entry; not useable for input) -->
  <t id="2025">/033</t><!-- black (technical entry) -->
</page>
<page id="5554302" title="Object Name Dynamic Expressions" descr="UT Command and Control" voice="no">
  <t id="1" comment="Setting:  Version Number of the Custom Expressions File - change this Entry to update the Result on all Objects upon loading a Savegame">0</t>
  <t id="2" comment="Setting:  Safe Expression converted into English? (default no, set to yes if you want to transfer your Save from another language than english to a Game in another Language)">no</t>
  <!-- NPC Skills
  S => Skill
  +
  B => Boarding NPC
  C  => Pilot,Captain (both are technically equal)
  D => Defense Officer
  E => Engineer
  M => Manager
  +
  A => All(Combined)
  B => Boarding
  C => Combat
  E => Engineering
  L => Leadership
  M => Managment
  N => Navigation
  O => Morale
  S => Science -->
  <t id="10">%SBA</t>
  <t id="11">%SBB</t>
  <t id="12">%SBC</t>
  <t id="13">%SBE</t>
  <t id="14">%SBL</t>
  <t id="15">%SBM</t>
  <t id="16">%SBN</t>
  <t id="17">%SBO</t>
  <t id="18">%SBS</t>
  <t id="20">%SCA</t>
  <t id="21">%SCB</t>
  <t id="22">%SCC</t>
  <t id="23">%SCE</t>
  <t id="24">%SCL</t>
  <t id="25">%SCM</t>
  <t id="26">%SCN</t>
  <t id="27">%SCO</t>
  <t id="28">%SCS</t>
  <t id="30">%SDA</t>
  <t id="31">%SDB</t>
  <t id="32">%SDC</t>
  <t id="33">%SDE</t>
  <t id="34">%SDL</t>
  <t id="35">%SDM</t>
  <t id="36">%SDN</t>
  <t id="37">%SDO</t>
  <t id="38">%SDS</t>
  <t id="40">%SEA</t>
  <t id="41">%SEB</t>
  <t id="42">%SEC</t>
  <t id="43">%SEE</t>
  <t id="44">%SEL</t>
  <t id="45">%SEM</t>
  <t id="46">%SEN</t>
  <t id="47">%SEO</t>
  <t id="48">%SES</t>
  <t id="50">%SMA</t>
  <t id="51">%SMB</t>
  <t id="52">%SMC</t>
  <t id="53">%SME</t>
  <t id="54">%SML</t>
  <t id="55">%SMM</t>
  <t id="56">%SMN</t>
  <t id="57">%SMO</t>
  <t id="58">%SMS</t>
  <!-- Dynamic Replacements other than Skills -->
  <t id="100">%superiorobject</t>
  <t id="101">%superiorzone</t>
  <t id="102">%superiorsector</t>
  <t id="103">%superiorcluster</t>
  <t id="104">%zone</t>
  <t id="105">%sector</t>
  <t id="106">%cluster</t>
  <t id="107">%type</t>
</page>
</language>
