<?xml version="1.0" encoding="UTF-8" ?>
<diff>
  <add sel="//cue[@name='DefaultComm']/actions/do_else">
            <do_if value="$actor.iscontrolentity and $actor.type == entitytype.manager and $actor.owner == faction.player">
              <add_player_choice text="{5554103,9}" section="cStaff_UT_CAC_Manager" position="1"/>
            </do_if>
  </add>
  <add sel="//cue[@name='SectionHandler']/actions/do_else" pos="before">
            <do_elseif value="event.param == 'cStaff_UT_CAC_Manager'">
              <signal_cue_instantly cue="md.UT_CAC_Manager.Main" param="$actor"/>
              <cancel_cue cue="OnPlatformPopulation_Staff"/>
            </do_elseif>
  </add>
  <add sel="//cue[@name='OnPlatformPopulation_Staff']/cues[not(cue/@name='NPC_Cancel_Dialogue_Tree')]" optional="true"><!-- Only add this if not already present (cue may also be provided by other Extensions)-->
        <cue name="NPC_Cancel_Dialogue_Tree">
          <conditions>
            <event_object_signalled object="$actor" param="'cancel Vanilla dialogue tree'"/>
          </conditions>
          <actions>
            <cancel_cue cue="OnPlatformPopulation_Staff"/>
          </actions>
        </cue>
  </add>
  
  <add sel="//cue[@name='OnBoardComm']/actions/remove_value[1]" pos="before">
            <do_if value="@player.platform.ship.buildmodule and @player.platform.ship.owner == faction.player and $actor.type == entitytype.defencecontrol">
              <add_player_choice text="'Standby here.'" section="cStaff_cac_standbyhere" position="right" comment="Standby here"/>
            </do_if>
            <do_if value="@player.platform.ship.buildmodule and @player.platform.ship.owner == faction.player and  $actor.type == entitytype.manager ">
              <add_player_choice text="'Work here and convert CV to UT CAC.'" section="cStaff_cac_standbyhere" position="top_right" comment="Standby here"/>
            </do_if>
  </add>
  <add sel="//cue[@name='OnBoardComm']/actions/do_elseif[@value='not player.platform']">
                <do_if value="$actor.type == entitytype.manager or $actor.type == entitytype.defencecontrol">
                  <find_ship name="$CV" space="player.zone" primarypurpose="objectpurpose.build" owner="faction.player"><match_distance object="player.primaryship" max="10km"/></find_ship>
                  <do_if value="$CV.exists">
                    <do_if value="$actor.type == entitytype.manager">
                      <do_if value=" $CV.architect.exists and not $CV.buildanchor">
                        <add_player_choice text="'Work on %1 and convert to UT CAC'.[$CV.name]" section="cStaff_cac_standbyoncv" position="right" choiceparam="$CV" comment="Stand by on nearby CV"/>
                      </do_if>
                    </do_if>
                    <do_else>
                     <add_player_choice text="'Stand by on %1'.[$CV.name]" section="cStaff_cac_standbyoncv" position="right" choiceparam="$CV" comment="Stand by on nearby CV"/>
                    </do_else>
                  </do_if>
                  <remove_value name="$CV"/>
                </do_if>
</add>
  <add sel="//cue[@name='SectionHandler']/actions/do_else" pos="before">
            <do_elseif value="event.param == 'cStaff_cac_standbyhere'">
              <add_npc_line line="3167" view="facenormal" comment="OK, sir. I'll move into my new quarters now." />
              <set_value name="$container" exact="player.platform.container" />
              <signal_cue_instantly cue="md.NPC_Staff.LogAssignedToObject" param="[$actor, $container]" />
              <add_actor_to_platform actor="$actor" dockingbay="player.platform" />
              <play_cutscene key="'LeavePlayerShip'">
                <param name="npcref" object="$actor" />
              </play_cutscene>
              <do_if value="$actor.type == entitytype.manager and player.platform.container.architect.exists">
                <signal_objects object="player.platform.container.architect" param="'cancel Vanilla dialogue tree'"/>
                <signal_cue_instantly cue="md.UT_CAC_Architect.Main" param="player.platform.container.architect"/>
                <cancel_cue cue="OnPlatformPopulation_Staff"/>
                <signal_cue_instantly cue="md.UT_CAC_Manager.Main" param="$actor"/>
              </do_if>
              <remove_value name="$container" />
            </do_elseif>
            <do_elseif value="event.param == 'cStaff_cac_standbyoncv'">
              <do_if value="$actor.type == entitytype.manager">
                <do_if value="event.param2.architect.exists">
                  <signal_cue_instantly cue="md.NPC_Staff.LogAssignedToObject" param="[$actor, event.param2]" />
                  <play_cutscene key="'LeavePlayerShipWithDrone'">
                    <param name="npcref" object="$actor" />
                  </play_cutscene>
                  <start_actor_transport actor="$actor" target="event.param2" />
                  <signal_objects object="event.param2.architect" param="'cancel Vanilla dialogue tree'"/>
                  <signal_cue_instantly cue="md.UT_CAC_Architect.Main" param="event.param2.architect"/>
                  <cancel_cue cue="OnPlatformPopulation_Staff"/>
                  <signal_cue_instantly cue="md.UT_CAC_Manager.Main" param="$actor"/>
                </do_if>
              </do_if>
              <do_else>
                <signal_cue_instantly cue="md.NPC_Staff.LogAssignedToObject" param="[$actor, event.param2]" />
                <play_cutscene key="'LeavePlayerShipWithDrone'">
                  <param name="npcref" object="$actor" />
                </play_cutscene>
                <start_actor_transport actor="$actor" target="event.param2" />
                <set_value name="$ut_cac_actorstandby"/>
              </do_else>
            </do_elseif>
  </add>
  <!-- prevent assigning as control entity when moved to a CV without changing the expression itself-->
  <!-- NOTE: COMPATIBILITY HERE WILL EASILY BREAK -->
  <add sel="//cue[@name='OnDroneArrival']/actions/do_if[2]" type="@chance">( not $ut_cac_actorstandby? ) * 100</add>
  <add sel="//cue[@name='OnDroneArrival']/actions" ><remove_value name="$ut_cac_actorstandby"/></add>
</diff>